fastDStool/__init__.py
fastDStool/fastDStool.py
fastDStool-1.0.1.dist-info/METADATA
fastDStool-1.0.1.dist-info/WHEEL
fastDStool-1.0.1.dist-info/top_level.txt
fastDStool-1.0.1.dist-info/RECORD
