Metadata-Version: 2.1
Name: fastDStool
Version: 1.0.1
Summary: find best parameters for data science at once
Home-page: https://github.com/yerinOneul/fastDStool
Author: yerin Hong
Author-email: yerinoneul@gmail.com
License: MIT
Platform: UNKNOWN
Classifier: Programming Language :: Python :: 3
Classifier: License :: OSI Approved :: MIT License
Classifier: Operating System :: OS Independent
Requires-Python: >=3
Requires-Dist: pandas
Requires-Dist: sklearn
